lanzou/__init__.py
lanzou/api/__init__.py
lanzou/api/core.py
lanzou/api/models.py
lanzou/api/types.py
lanzou/api/utils.py
olz-0.0.1.dist-info/LICENSE
olz-0.0.1.dist-info/METADATA
olz-0.0.1.dist-info/WHEEL
olz-0.0.1.dist-info/top_level.txt
olz-0.0.1.dist-info/RECORD
