Metadata-Version: 2.1
Name: olz
Version: 0.0.1
Summary: 蓝奏云网盘第三方API，2025年修复版本
Home-page: https://github.com/HG-ha/olz
Author: YiMing
Author-email: 1790233968@qq.com
License: UNKNOWN
Platform: UNKNOWN
Classifier: Programming Language :: Python :: 3.7
Classifier: Operating System :: OS Independent
Requires-Dist: requests >=2.0.0
